lcd_ctrl.v
module lcd_ctrl(clk, reset, datain, cmd, cmd_valid, dataout, output_valid, busy);
input           clk;
input           reset;
input   [7:0]   datain;
input   [2:0]   cmd;
input           cmd_valid;
output  reg     [7:0]dataout;
output  reg     output_valid;
output  reg     busy;
reg   [7:0]buffer[35:0];   
reg   [5:0]count;
reg   [3:0]out_count;
reg   [5:0]origin;
reg   valid;

parameter reflash = 3'd0,
          load = 3'd1,
          right = 3'd2,
          left = 3'd3,
          up = 3'd4,
          down = 3'd5;  
integer i;

always@(posedge clk)
  begin
    if(reset)
      begin
        origin <= 6'd0;
        valid <= 1'b0;
        output_valid <= 1'b0;  
        out_count <= 4'd0; 
        busy <= 1'b0;      
        count <= 6'd0;  
        for(i = 0; i < 36; i = i + 1)
          begin
            buffer[i] <= 0;
        end 
    end
    else
      begin
        if(cmd_valid)
          begin
            if(!busy)
              begin
                busy <= 1'b1;
                case(cmd)
                  reflash:begin
                    origin <= origin;
                    output_valid <= 1'b1;
                  end
                  load:begin          
                    origin <= 6'd14;
                    valid <= 1'b1;  
                    output_valid <= 1'b0; 
                  end
                  right:begin
                    if(origin == 6'd3 || origin == 6'd9 || origin == 6'd15 || origin == 6'd21)
                      origin <= origin;
                    else
                      origin <= origin + 1;
                    output_valid <= 1'b1;
                  end
                  left:begin
                    if(origin == 6'd0 || origin == 6'd6 || origin == 6'd12 || origin == 6'd18)
                      origin <= origin;
                    else
                      origin <= origin - 1;
                    output_valid <= 1'b1;
                  end
                  up:begin
                    if(origin == 6'd0 || origin == 6'd1 || origin == 6'd2 || origin == 6'd3)
                      origin <= origin;
                    else
                      origin <= origin - 6;
                    output_valid <= 1'b1;
                  end
                  down:begin
                    if(origin == 6'd18 || origin == 6'd19 || origin == 6'd20 || origin == 6'd21)
                      origin <= origin;
                    else
                      origin <= origin + 6;
                    output_valid <= 1'b1;
                  end
                  default:begin
                    origin <= origin;
                    output_valid <= 1'b0;
                  end
                endcase
            end
            else
              begin
                origin <= origin;
                valid <= valid;
                output_valid <= output_valid;
            end
        end 
        else
          begin
            output_valid <= output_valid;
            origin <= origin;
            valid <= valid;
            if(valid)
              begin
                busy <= 1'b1;
                if(count == 6'd36)
                  begin
                    count <= count;
                    output_valid <= 1'b1;
                    valid <= 1'b0;
                end
       	        else
                  begin         
                    buffer[count] <= datain;
                    count <= count + 1;
                    output_valid <= 1'b0;
                end
            end
            else
              begin
                if(output_valid)
                  begin  
                    if(out_count == 4'd8)
                      begin                     
                        busy <= 1'b0;
                        output_valid <= 1'b0;
                        out_count <= 4'd0;
                        count <= 6'd0;
                        origin <= origin - 14;
                    end
                    else 
                      begin                       
              	         busy <= 1'b1;
              	         out_count <= out_count + 1'b1;
                        if(out_count == 4'd2 || out_count == 4'd5)
              	           begin
                            origin <= origin + 4;
                        end               	 	 	
                        else
                          begin             
                            origin <= origin + 1; 
                    	   end
                    end
                end
                else
                  begin
                    origin <= origin;
                    valid <= valid;
                   	output_valid <= output_valid;
                end
          	 end
        end
    end
end  
always@(negedge clk)
begin
  if(reset)
      dataout <= 8'd0;     
  else
    begin
    if(valid)
        dataout <= 8'd0;
    else
        dataout <= buffer[origin];
  end 
end                                                                             
endmodule

testfixture.v
`timescale 1ns/10ps
`define CYCLE    100                        // Modify your clock period here
`define SDFFILE  "./lcd_ctrl_syn.sdf"	    // Modify your sdf file name
`define IMAGE    "./image1.dat"             // Modify your test image file: image1.dat or image2.dat
`define CMD      "./cmd1.dat"               // Modify your test cmd file: cmd1.dat or cmd2.dat
`define EXPECT   "./out_golden1.dat"        // Modify your output golden file: out_golden1.dat or out_golden2.dat

module test;
parameter IMAGE_N_PAT = 36;         // 6x6 = 36 pixels
parameter CMD_N_PAT = 30;           // number of commands
parameter OUT_LENGTH = 270;         // output length = (3x3) * CMD_N_PAT
parameter t_reset = `CYCLE*2;

reg           clk;
reg           reset;
reg   [7:0]   datain;
reg   [2:0]   cmd;
reg           cmd_valid;
wire  [7:0]   dataout;
wire          output_valid;
wire          busy;

reg   [7:0]   image_mem [0:IMAGE_N_PAT-1];
reg   [2:0]   cmd_mem   [0:CMD_N_PAT-1];
reg   [7:0]   out_mem   [0:OUT_LENGTH-1];
reg   [7:0]   out_temp;

reg           stop;
integer       i, j, out_f, err, pattern_num;
reg           over;

   lcd_ctrl top(.clk(clk), .reset(reset), .datain(datain), 
                .cmd(cmd), .cmd_valid(cmd_valid), .dataout(dataout), 
                .output_valid(output_valid), .busy(busy));          
   


//initial $sdf_annotate(`SDFFILE, top);

initial	$readmemh (`IMAGE,  image_mem);
initial	$readmemh (`CMD,    cmd_mem);
initial	$readmemh (`EXPECT, out_mem);

initial begin
   clk         = 1'b0;
   reset       = 1'b0;
   cmd_valid   = 1'b0;
   stop        = 1'b0;  
   over        = 1'b0;
   pattern_num = 0;
   err         = 0;    
end

always begin #(`CYCLE/2) clk = ~clk; end

initial begin
$dumpfile("LCD_CTRL.vcd");
$dumpvars;
//$fsdbDumpfile("LCD_CTRL.fsdb");
//$fsdbDumpvars;

   out_f = $fopen("out.dat");
   if (out_f == 0) begin
        $display("Output file open error !");
        $finish;
   end
end


initial begin
   @(negedge clk)  reset = 1'b1;
   #t_reset        reset = 1'b0;
   
   @(negedge clk)    i=0;
   while (i <= CMD_N_PAT) begin               
      if(!busy) begin
        cmd = cmd_mem[i];
        cmd_valid = 1'b1;  
        
        if(cmd_mem[i] === 3'h1) begin    //cmd: Load data        
           for(j=0; j<=IMAGE_N_PAT; j=j+1)begin
              @(negedge clk) datain = image_mem[j];
                             cmd = 'hz; cmd_valid = 1'b0;
           end
           i = i+1;
        end
        else begin                      //cmd: other command
           @(negedge clk) datain='hz; cmd_valid = 1'b0; i = i+1;
        end       
      end 
      else begin
         datain='hz; cmd = 'hz;  cmd_valid = 0;
         @(negedge clk);
      end               
    end                                       
    stop = 1 ;      
end

always @(posedge clk)begin
   out_temp = out_mem[pattern_num];
   if(output_valid)begin
      $fdisplay(out_f,"%h", dataout);
      if(dataout !== out_temp) begin
         $display("ERROR at %d:output %h !=expect %h ",pattern_num, dataout, out_temp);
         err = err + 1 ;
      end
      pattern_num = pattern_num + 1;      
   end
   if(pattern_num === OUT_LENGTH)  over = 1'b1;
end


initial begin
      @(posedge stop)      
      if((over) || (pattern_num!='h0)) begin
         $display("---------------------------------------------\n");
         if (err == 0)  begin
            $display("All data have been generated successfully!\n");
            $display("-------------------PASS-------------------\n");
         end
         else 
            $display("There are %d errors!\n", err);
            $display("---------------------------------------------\n");
      end
      else begin
        $display("---------------------------------------------\n");
        $display("Error!!! There is no any data output ...!\n");
        $display("-------------------FAIL-------------------\n");
        $display("---------------------------------------------\n");
      end
      $finish;
end
   
endmodule

LCD_CTRL.vcd
$date
	Wed Aug 05 12:20:21 2020
$end
$version
	ModelSim Version 10.1c
$end
$timescale
	10ps
$end
$scope module test $end
$var parameter 32 ! IMAGE_N_PAT $end
$var parameter 32 " CMD_N_PAT $end
$var parameter 32 # OUT_LENGTH $end
$var parameter 32 $ t_reset $end
$var reg 1 % clk $end
$var reg 1 & reset $end
$var reg 8 ' datain [7:0] $end
$var reg 3 ( cmd [2:0] $end
$var reg 1 ) cmd_valid $end
$var wire 1 * dataout [7] $end
$var wire 1 + dataout [6] $end
$var wire 1 , dataout [5] $end
$var wire 1 - dataout [4] $end
$var wire 1 . dataout [3] $end
$var wire 1 / dataout [2] $end
$var wire 1 0 dataout [1] $end
$var wire 1 1 dataout [0] $end
$var wire 1 2 output_valid $end
$var wire 1 3 busy $end
$var reg 8 4 out_temp [7:0] $end
$var reg 1 5 stop $end
$var integer 32 6 i $end
$var integer 32 7 j $end
$var integer 32 8 out_f $end
$var integer 32 9 err $end
$var integer 32 : pattern_num $end
$var reg 1 ; over $end
$scope module top $end
$var parameter 3 < reflash $end
$var parameter 3 = load $end
$var parameter 3 > right $end
$var parameter 3 ? left $end
$var parameter 3 @ up $end
$var parameter 3 A down $end
$var wire 1 B clk $end
$var wire 1 C reset $end
$var wire 1 D datain [7] $end
$var wire 1 E datain [6] $end
$var wire 1 F datain [5] $end
$var wire 1 G datain [4] $end
$var wire 1 H datain [3] $end
$var wire 1 I datain [2] $end
$var wire 1 J datain [1] $end
$var wire 1 K datain [0] $end
$var wire 1 L cmd [2] $end
$var wire 1 M cmd [1] $end
$var wire 1 N cmd [0] $end
$var wire 1 O cmd_valid $end
$var reg 8 P dataout [7:0] $end
$var reg 1 Q output_valid $end
$var reg 1 R busy $end
$var reg 6 S count [5:0] $end
$var reg 4 T out_count [3:0] $end
$var reg 6 U origin [5:0] $end
$var reg 1 V valid $end
$var integer 32 W i $end
$upscope $end
$upscope $end
$enddefinitions $end
#0
$dumpvars
0%
0&
bx '
bx (
0)
bx 4
05
0;
bx P
xQ
xR
bx S
bx T
bx U
xV
b100100 !
b11110 "
b100001110 #
b11001000 $
b0 <
b1 =
b10 >
b11 ?
b100 @
b101 A
bx 6
bx 7
b10 8
b0 9
b0 :
bx W
x1
x0
x/
x.
x-
x,
x+
x*
x2
x3
0O
xN
xM
xL
xK
xJ
xI
xH
xG
xF
xE
xD
0C
0B
$end
#5000
1%
1B
b1110 4
#10000
0%
0B
1&
1C
#15000
1%
1B
b0 W
b1 W
b10 W
b11 W
b100 W
b101 W
b110 W
b111 W
b1000 W
b1001 W
b1010 W
b1011 W
b1100 W
b1101 W
b1110 W
b1111 W
b10000 W
b10001 W
b10010 W
b10011 W
b10100 W
b10101 W
b10110 W
b10111 W
b11000 W
b11001 W
b11010 W
b11011 W
b11100 W
b11101 W
b11110 W
b11111 W
b100000 W
b100001 W
b100010 W
b100011 W
b100100 W
b0 U
0V
0Q
b0 T
0R
b0 S
02
03
#20000
0%
0B
b0 P
01
00
0/
0.
0-
0,
0+
0*
#25000
1%
1B
b0 W
b1 W
b10 W
b11 W
b100 W
b101 W
b110 W
b111 W
b1000 W
b1001 W
b1010 W
b1011 W
b1100 W
b1101 W
b1110 W
b1111 W
b10000 W
b10001 W
b10010 W
b10011 W
b10100 W
b10101 W
b10110 W
b10111 W
b11000 W
b11001 W
b11010 W
b11011 W
b11100 W
b11101 W
b11110 W
b11111 W
b100000 W
b100001 W
b100010 W
b100011 W
b100100 W
#30000
0&
0%
0C
0B
b0 6
b1 (
1)
b0 7
1N
0M
0L
1O
#35000
1%
1B
1R
b1110 U
1V
13
#40000
0%
0B
b0 '
bz (
0)
b1 7
zN
zM
zL
0K
0J
0I
0H
0G
0F
0E
0D
0O
#45000
1%
1B
b1 S
#50000
0%
0B
b1 '
b10 7
1K
#55000
1%
1B
b10 S
#60000
0%
0B
b10 '
b11 7
0K
1J
#65000
1%
1B
b11 S
#70000
0%
0B
b11 '
b100 7
1K
#75000
1%
1B
b100 S
#80000
0%
0B
b100 '
b101 7
0K
0J
1I
#85000
1%
1B
b101 S
#90000
0%
0B
b101 '
b110 7
1K
#95000
1%
1B
b110 S
#100000
0%
0B
b110 '
b111 7
0K
1J
#105000
1%
1B
b111 S
#110000
0%
0B
b111 '
b1000 7
1K
#115000
1%
1B
b1000 S
#120000
0%
0B
b1000 '
b1001 7
0K
0J
0I
1H
#125000
1%
1B
b1001 S
#130000
0%
0B
b1001 '
b1010 7
1K
#135000
1%
1B
b1010 S
#140000
0%
0B
b1010 '
b1011 7
0K
1J
#145000
1%
1B
b1011 S
#150000
0%
0B
b1011 '
b1100 7
1K
#155000
1%
1B
b1100 S
#160000
0%
0B
b1100 '
b1101 7
0K
0J
1I
#165000
1%
1B
b1101 S
#170000
0%
0B
b1101 '
b1110 7
1K
#175000
1%
1B
b1110 S
#180000
0%
0B
b1110 '
b1111 7
0K
1J
#185000
1%
1B
b1111 S
#190000
0%
0B
b1111 '
b10000 7
1K
#195000
1%
1B
b10000 S
#200000
0%
0B
b10000 '
b10001 7
0K
0J
0I
0H
1G
#205000
1%
1B
b10001 S
#210000
0%
0B
b10001 '
b10010 7
1K
#215000
1%
1B
b10010 S
#220000
0%
0B
b10010 '
b10011 7
0K
1J
#225000
1%
1B
b10011 S
#230000
0%
0B
b10011 '
b10100 7
1K
#235000
1%
1B
b10100 S
#240000
0%
0B
b10100 '
b10101 7
0K
0J
1I
#245000
1%
1B
b10101 S
#250000
0%
0B
b10101 '
b10110 7
1K
#255000
1%
1B
b10110 S
#260000
0%
0B
b10110 '
b10111 7
0K
1J
#265000
1%
1B
b10111 S
#270000
0%
0B
b10111 '
b11000 7
1K
#275000
1%
1B
b11000 S
#280000
0%
0B
b11000 '
b11001 7
0K
0J
0I
1H
#285000
1%
1B
b11001 S
#290000
0%
0B
b11001 '
b11010 7
1K
#295000
1%
1B
b11010 S
#300000
0%
0B
b11010 '
b11011 7
0K
1J
#305000
1%
1B
b11011 S
#310000
0%
0B
b11011 '
b11100 7
1K
#315000
1%
1B
b11100 S
#320000
0%
0B
b11100 '
b11101 7
0K
0J
1I
#325000
1%
1B
b11101 S
#330000
0%
0B
b11101 '
b11110 7
1K
#335000
1%
1B
b11110 S
#340000
0%
0B
b11110 '
b11111 7
0K
1J
#345000
1%
1B
b11111 S
#350000
0%
0B
b11111 '
b100000 7
1K
#355000
1%
1B
b100000 S
#360000
0%
0B
b100000 '
b100001 7
0K
0J
0I
0H
0G
1F
#365000
1%
1B
b100001 S
#370000
0%
0B
b100001 '
b100010 7
1K
#375000
1%
1B
b100010 S
#380000
0%
0B
b100010 '
b100011 7
0K
1J
#385000
1%
1B
b100011 S
#390000
0%
0B
b100011 '
b100100 7
1K
#395000
1%
1B
b100100 S
#400000
0%
0B
bx '
b100101 7
b1 6
bz '
zK
zJ
zI
zH
zG
zF
zE
zD
#405000
1%
1B
1Q
0V
12
#410000
0%
0B
b1110 P
10
1/
1.
#415000
1%
1B
b1 :
b1 T
b1111 U
#420000
0%
0B
b1111 P
11
#425000
1%
1B
b1111 4
b10 :
b10 T
b10000 U
#430000
0%
0B
b10000 P
01
00
0/
0.
1-
#435000
1%
1B
b10000 4
b11 :
b11 T
b10100 U
#440000
0%
0B
b10100 P
1/
#445000
1%
1B
b10100 4
b100 :
b100 T
b10101 U
#450000
0%
0B
b10101 P
11
#455000
1%
1B
b10101 4
b101 :
b101 T
b10110 U
#460000
0%
0B
b10110 P
01
10
#465000
1%
1B
b10110 4
b110 :
b110 T
b11010 U
#470000
0%
0B
b11010 P
0/
1.
#475000
1%
1B
b11010 4
b111 :
b111 T
b11011 U
#480000
0%
0B
b11011 P
11
#485000
1%
1B
b11011 4
b1000 :
b1000 T
b11100 U
#490000
0%
0B
b11100 P
01
00
1/
#495000
1%
1B
b11100 4
b1001 :
0R
0Q
b0 T
b0 S
b1110 U
03
02
#500000
0%
0B
b10 (
1)
0N
1M
0L
1O
b1110 P
10
0-
#505000
1%
1B
b1111 4
1R
b1111 U
1Q
13
12
#510000
0%
0B
0)
b10 6
bz (
0O
zN
zM
zL
b1111 P
11
#515000
1%
1B
b1010 :
b1 T
b10000 U
#520000
0%
0B
b10000 P
01
00
0/
0.
1-
#525000
1%
1B
b10000 4
b1011 :
b10 T
b10001 U
#530000
0%
0B
b10001 P
11
#535000
1%
1B
b10001 4
b1100 :
b11 T
b10101 U
#540000
0%
0B
b10101 P
1/
#545000
1%
1B
b10101 4
b1101 :
b100 T
b10110 U
#550000
0%
0B
b10110 P
01
10
#555000
1%
1B
b10110 4
b1110 :
b101 T
b10111 U
#560000
0%
0B
b10111 P
11
#565000
1%
1B
b10111 4
b1111 :
b110 T
b11011 U
#570000
0%
0B
b11011 P
0/
1.
#575000
1%
1B
b11011 4
b10000 :
b111 T
b11100 U
#580000
0%
0B
b11100 P
01
00
1/
#585000
1%
1B
b11100 4
b10001 :
b1000 T
b11101 U
#590000
0%
0B
b11101 P
11
#595000
1%
1B
b11101 4
b10010 :
0R
0Q
b0 T
b1111 U
03
02
#600000
0%
0B
b101 (
1)
1N
0M
1L
1O
b1111 P
10
0-
#605000
1%
1B
b10101 4
1R
b10101 U
1Q
13
12
#610000
0%
0B
0)
b11 6
bz (
0O
zN
zM
zL
b10101 P
00
0.
1-
#615000
1%
1B
b10011 :
b1 T
b10110 U
#620000
0%
0B
b10110 P
01
10
#625000
1%
1B
b10110 4
b10100 :
b10 T
b10111 U
#630000
0%
0B
b10111 P
11
#635000
1%
1B
b10111 4
b10101 :
b11 T
b11011 U
#640000
0%
0B
b11011 P
0/
1.
#645000
1%
1B
b11011 4
b10110 :
b100 T
b11100 U
#650000
0%
0B
b11100 P
01
00
1/
#655000
1%
1B
b11100 4
b10111 :
b101 T
b11101 U
#660000
0%
0B
b11101 P
11
#665000
1%
1B
b11101 4
b11000 :
b110 T
b100001 U
#670000
0%
0B
b100001 P
0/
0.
0-
1,
#675000
1%
1B
b100001 4
b11001 :
b111 T
b100010 U
#680000
0%
0B
b100010 P
01
10
#685000
1%
1B
b100010 4
b11010 :
b1000 T
b100011 U
#690000
0%
0B
b100011 P
11
#695000
1%
1B
b100011 4
b11011 :
0R
0Q
b0 T
b10101 U
03
02
#700000
0%
0B
b11 (
1)
1N
1M
0L
1O
b10101 P
00
1/
1-
0,
#705000
1%
1B
b10100 4
1R
b10100 U
1Q
13
12
#710000
0%
0B
0)
b100 6
bz (
0O
zN
zM
zL
b10100 P
01
#715000
1%
1B
b11100 :
b1 T
b10101 U
#720000
0%
0B
b10101 P
11
#725000
1%
1B
b10101 4
b11101 :
b10 T
b10110 U
#730000
0%
0B
b10110 P
01
10
#735000
1%
1B
b10110 4
b11110 :
b11 T
b11010 U
#740000
0%
0B
b11010 P
0/
1.
#745000
1%
1B
b11010 4
b11111 :
b100 T
b11011 U
#750000
0%
0B
b11011 P
11
#755000
1%
1B
b11011 4
b100000 :
b101 T
b11100 U
#760000
0%
0B
b11100 P
01
00
1/
#765000
1%
1B
b11100 4
b100001 :
b110 T
b100000 U
#770000
0%
0B
b100000 P
0/
0.
0-
1,
#775000
1%
1B
b100000 4
b100010 :
b111 T
b100001 U
#780000
0%
0B
b100001 P
11
#785000
1%
1B
b100001 4
b100011 :
b1000 T
b100010 U
#790000
0%
0B
b100010 P
01
10
#795000
1%
1B
b100010 4
b100100 :
0R
0Q
b0 T
b10100 U
03
02
#800000
0%
0B
b100 (
1)
0N
0M
1L
1O
b10100 P
00
1/
1-
0,
#805000
1%
1B
b1110 4
1R
b1110 U
1Q
13
12
#810000
0%
0B
0)
b101 6
bz (
0O
zN
zM
zL
b1110 P
10
1.
0-
#815000
1%
1B
b100101 :
b1 T
b1111 U
#820000
0%
0B
b1111 P
11
#825000
1%
1B
b1111 4
b100110 :
b10 T
b10000 U
#830000
0%
0B
b10000 P
01
00
0/
0.
1-
#835000
1%
1B
b10000 4
b100111 :
b11 T
b10100 U
#840000
0%
0B
b10100 P
1/
#845000
1%
1B
b10100 4
b101000 :
b100 T
b10101 U
#850000
0%
0B
b10101 P
11
#855000
1%
1B
b10101 4
b101001 :
b101 T
b10110 U
#860000
0%
0B
b10110 P
01
10
#865000
1%
1B
b10110 4
b101010 :
b110 T
b11010 U
#870000
0%
0B
b11010 P
0/
1.
#875000
1%
1B
b11010 4
b101011 :
b111 T
b11011 U
#880000
0%
0B
b11011 P
11
#885000
1%
1B
b11011 4
b101100 :
b1000 T
b11100 U
#890000
0%
0B
b11100 P
01
00
1/
#895000
1%
1B
b11100 4
b101101 :
0R
0Q
b0 T
b1110 U
03
02
#900000
0%
0B
b0 (
1)
0N
0M
0L
1O
b1110 P
10
0-
#905000
1%
1B
b1110 4
1R
1Q
13
12
#910000
0%
0B
0)
b110 6
bz (
0O
zN
zM
zL
#915000
1%
1B
b101110 :
b1 T
b1111 U
#920000
0%
0B
b1111 P
11
#925000
1%
1B
b1111 4
b101111 :
b10 T
b10000 U
#930000
0%
0B
b10000 P
01
00
0/
0.
1-
#935000
1%
1B
b10000 4
b110000 :
b11 T
b10100 U
#940000
0%
0B
b10100 P
1/
#945000
1%
1B
b10100 4
b110001 :
b100 T
b10101 U
#950000
0%
0B
b10101 P
11
#955000
1%
1B
b10101 4
b110010 :
b101 T
b10110 U
#960000
0%
0B
b10110 P
01
10
#965000
1%
1B
b10110 4
b110011 :
b110 T
b11010 U
#970000
0%
0B
b11010 P
0/
1.
#975000
1%
1B
b11010 4
b110100 :
b111 T
b11011 U
#980000
0%
0B
b11011 P
11
#985000
1%
1B
b11011 4
b110101 :
b1000 T
b11100 U
#990000
0%
0B
b11100 P
01
00
1/
#995000
1%
1B
b11100 4
b110110 :
0R
0Q
b0 T
b1110 U
03
02
#1000000
0%
0B
b1 (
1)
b0 7
1N
0M
0L
1O
b1110 P
10
0-
#1005000
1%
1B
b1110 4
1R
1V
13
#1010000
0%
0B
b0 '
bz (
0)
b1 7
zN
zM
zL
0K
0J
0I
0H
0G
0F
0E
0D
0O
b0 P
00
0/
0.
#1015000
1%
1B
b1 S
#1020000
0%
0B
b1 '
b10 7
1K
#1025000
1%
1B
b10 S
#1030000
0%
0B
b10 '
b11 7
0K
1J
#1035000
1%
1B
b11 S
#1040000
0%
0B
b11 '
b100 7
1K
#1045000
1%
1B
b100 S
#1050000
0%
0B
b100 '
b101 7
0K
0J
1I
#1055000
1%
1B
b101 S
#1060000
0%
0B
b101 '
b110 7
1K
#1065000
1%
1B
b110 S
#1070000
0%
0B
b110 '
b111 7
0K
1J
#1075000
1%
1B
b111 S
#1080000
0%
0B
b111 '
b1000 7
1K
#1085000
1%
1B
b1000 S
#1090000
0%
0B
b1000 '
b1001 7
0K
0J
0I
1H
#1095000
1%
1B
b1001 S
#1100000
0%
0B
b1001 '
b1010 7
1K
#1105000
1%
1B
b1010 S
#1110000
0%
0B
b1010 '
b1011 7
0K
1J
#1115000
1%
1B
b1011 S
#1120000
0%
0B
b1011 '
b1100 7
1K
#1125000
1%
1B
b1100 S
#1130000
0%
0B
b1100 '
b1101 7
0K
0J
1I
#1135000
1%
1B
b1101 S
#1140000
0%
0B
b1101 '
b1110 7
1K
#1145000
1%
1B
b1110 S
#1150000
0%
0B
b1110 '
b1111 7
0K
1J
#1155000
1%
1B
b1111 S
#1160000
0%
0B
b1111 '
b10000 7
1K
#1165000
1%
1B
b10000 S
#1170000
0%
0B
b10000 '
b10001 7
0K
0J
0I
0H
1G
#1175000
1%
1B
b10001 S
#1180000
0%
0B
b10001 '
b10010 7
1K
#1185000
1%
1B
b10010 S
#1190000
0%
0B
b10010 '
b10011 7
0K
1J
#1195000
1%
1B
b10011 S
#1200000
0%
0B
b10011 '
b10100 7
1K
#1205000
1%
1B
b10100 S
#1210000
0%
0B
b10100 '
b10101 7
0K
0J
1I
#1215000
1%
1B
b10101 S
#1220000
0%
0B
b10101 '
b10110 7
1K
#1225000
1%
1B
b10110 S
#1230000
0%
0B
b10110 '
b10111 7
0K
1J
#1235000
1%
1B
b10111 S
#1240000
0%
0B
b10111 '
b11000 7
1K
#1245000
1%
1B
b11000 S
#1250000
0%
0B
b11000 '
b11001 7
0K
0J
0I
1H
#1255000
1%
1B
b11001 S
#1260000
0%
0B
b11001 '
b11010 7
1K
#1265000
1%
1B
b11010 S
#1270000
0%
0B
b11010 '
b11011 7
0K
1J
#1275000
1%
1B
b11011 S
#1280000
0%
0B
b11011 '
b11100 7
1K
#1285000
1%
1B
b11100 S
#1290000
0%
0B
b11100 '
b11101 7
0K
0J
1I
#1295000
1%
1B
b11101 S
#1300000
0%
0B
b11101 '
b11110 7
1K
#1305000
1%
1B
b11110 S
#1310000
0%
0B
b11110 '
b11111 7
0K
1J
#1315000
1%
1B
b11111 S
#1320000
0%
0B
b11111 '
b100000 7
1K
#1325000
1%
1B
b100000 S
#1330000
0%
0B
b100000 '
b100001 7
0K
0J
0I
0H
0G
1F
#1335000
1%
1B
b100001 S
#1340000
0%
0B
b100001 '
b100010 7
1K
#1345000
1%
1B
b100010 S
#1350000
0%
0B
b100010 '
b100011 7
0K
1J
#1355000
1%
1B
b100011 S
#1360000
0%
0B
b100011 '
b100100 7
1K
#1365000
1%
1B
b100100 S
#1370000
0%
0B
bx '
b100101 7
b111 6
bz '
zK
zJ
zI
zH
zG
zF
zE
zD
#1375000
1%
1B
1Q
0V
12
#1380000
0%
0B
b1110 P
10
1/
1.
#1385000
1%
1B
b110111 :
b1 T
b1111 U
#1390000
0%
0B
b1111 P
11
#1395000
1%
1B
b1111 4
b111000 :
b10 T
b10000 U
#1400000
0%
0B
b10000 P
01
00
0/
0.
1-
#1405000
1%
1B
b10000 4
b111001 :
b11 T
b10100 U
#1410000
0%
0B
b10100 P
1/
#1415000
1%
1B
b10100 4
b111010 :
b100 T
b10101 U
#1420000
0%
0B
b10101 P
11
#1425000
1%
1B
b10101 4
b111011 :
b101 T
b10110 U
#1430000
0%
0B
b10110 P
01
10
#1435000
1%
1B
b10110 4
b111100 :
b110 T
b11010 U
#1440000
0%
0B
b11010 P
0/
1.
#1445000
1%
1B
b11010 4
b111101 :
b111 T
b11011 U
#1450000
0%
0B
b11011 P
11
#1455000
1%
1B
b11011 4
b111110 :
b1000 T
b11100 U
#1460000
0%
0B
b11100 P
01
00
1/
#1465000
1%
1B
b11100 4
b111111 :
0R
0Q
b0 T
b0 S
b1110 U
03
02
#1470000
0%
0B
b11 (
1)
1N
1M
0L
1O
b1110 P
10
0-
#1475000
1%
1B
b1101 4
1R
b1101 U
1Q
13
12
#1480000
0%
0B
0)
b1000 6
bz (
0O
zN
zM
zL
b1101 P
11
00
#1485000
1%
1B
b1000000 :
b1 T
b1110 U
#1490000
0%
0B
b1110 P
01
10
#1495000
1%
1B
b1110 4
b1000001 :
b10 T
b1111 U
#1500000
0%
0B
b1111 P
11
#1505000
1%
1B
b1111 4
b1000010 :
b11 T
b10011 U
#1510000
0%
0B
b10011 P
0/
0.
1-
#1515000
1%
1B
b10011 4
b1000011 :
b100 T
b10100 U
#1520000
0%
0B
b10100 P
01
00
1/
#1525000
1%
1B
b10100 4
b1000100 :
b101 T
b10101 U
#1530000
0%
0B
b10101 P
11
#1535000
1%
1B
b10101 4
b1000101 :
b110 T
b11001 U
#1540000
0%
0B
b11001 P
0/
1.
#1545000
1%
1B
b11001 4
b1000110 :
b111 T
b11010 U
#1550000
0%
0B
b11010 P
01
10
#1555000
1%
1B
b11010 4
b1000111 :
b1000 T
b11011 U
#1560000
0%
0B
b11011 P
11
#1565000
1%
1B
b11011 4
b1001000 :
0R
0Q
b0 T
b1101 U
03
02
#1570000
0%
0B
b101 (
1)
1N
0M
1L
1O
b1101 P
00
1/
0-
#1575000
1%
1B
b10011 4
1R
b10011 U
1Q
13
12
#1580000
0%
0B
0)
b1001 6
bz (
0O
zN
zM
zL
b10011 P
10
0/
0.
1-
#1585000
1%
1B
b1001001 :
b1 T
b10100 U
#1590000
0%
0B
b10100 P
01
00
1/
#1595000
1%
1B
b10100 4
b1001010 :
b10 T
b10101 U
#1600000
0%
0B
b10101 P
11
#1605000
1%
1B
b10101 4
b1001011 :
b11 T
b11001 U
#1610000
0%
0B
b11001 P
0/
1.
#1615000
1%
1B
b11001 4
b1001100 :
b100 T
b11010 U
#1620000
0%
0B
b11010 P
01
10
#1625000
1%
1B
b11010 4
b1001101 :
b101 T
b11011 U
#1630000
0%
0B
b11011 P
11
#1635000
1%
1B
b11011 4
b1001110 :
b110 T
b11111 U
#1640000
0%
0B
b11111 P
1/
#1645000
1%
1B
b11111 4
b1001111 :
b111 T
b100000 U
#1650000
0%
0B
b100000 P
01
00
0/
0.
0-
1,
#1655000
1%
1B
b100000 4
b1010000 :
b1000 T
b100001 U
#1660000
0%
0B
b100001 P
11
#1665000
1%
1B
b100001 4
b1010001 :
0R
0Q
b0 T
b10011 U
03
02
#1670000
0%
0B
b101 (
1)
1N
0M
1L
1O
b10011 P
10
1-
0,
#1675000
1%
1B
b10011 4
1R
1Q
13
12
#1680000
0%
0B
0)
b1010 6
bz (
0O
zN
zM
zL
#1685000
1%
1B
b1010010 :
b1 T
b10100 U
#1690000
0%
0B
b10100 P
01
00
1/
#1695000
1%
1B
b10100 4
b1010011 :
b10 T
b10101 U
#1700000
0%
0B
b10101 P
11
#1705000
1%
1B
b10101 4
b1010100 :
b11 T
b11001 U
#1710000
0%
0B
b11001 P
0/
1.
#1715000
1%
1B
b11001 4
b1010101 :
b100 T
b11010 U
#1720000
0%
0B
b11010 P
01
10
#1725000
1%
1B
b11010 4
b1010110 :
b101 T
b11011 U
#1730000
0%
0B
b11011 P
11
#1735000
1%
1B
b11011 4
b1010111 :
b110 T
b11111 U
#1740000
0%
0B
b11111 P
1/
#1745000
1%
1B
b11111 4
b1011000 :
b111 T
b100000 U
#1750000
0%
0B
b100000 P
01
00
0/
0.
0-
1,
#1755000
1%
1B
b100000 4
b1011001 :
b1000 T
b100001 U
#1760000
0%
0B
b100001 P
11
#1765000
1%
1B
b100001 4
b1011010 :
0R
0Q
b0 T
b10011 U
03
02
#1770000
0%
0B
b11 (
1)
1N
1M
0L
1O
b10011 P
10
1-
0,
#1775000
1%
1B
b10010 4
1R
b10010 U
1Q
13
12
#1780000
0%
0B
0)
b1011 6
bz (
0O
zN
zM
zL
b10010 P
01
#1785000
1%
1B
b1011011 :
b1 T
b10011 U
#1790000
0%
0B
b10011 P
11
#1795000
1%
1B
b10011 4
b1011100 :
b10 T
b10100 U
#1800000
0%
0B
b10100 P
01
00
1/
#1805000
1%
1B
b10100 4
b1011101 :
b11 T
b11000 U
#1810000
0%
0B
b11000 P
0/
1.
#1815000
1%
1B
b11000 4
b1011110 :
b100 T
b11001 U
#1820000
0%
0B
b11001 P
11
#1825000
1%
1B
b11001 4
b1011111 :
b101 T
b11010 U
#1830000
0%
0B
b11010 P
01
10
#1835000
1%
1B
b11010 4
b1100000 :
b110 T
b11110 U
#1840000
0%
0B
b11110 P
1/
#1845000
1%
1B
b11110 4
b1100001 :
b111 T
b11111 U
